shllm.py
shllm-0.0.8.dist-info/METADATA
shllm-0.0.8.dist-info/WHEEL
shllm-0.0.8.dist-info/entry_points.txt
shllm-0.0.8.dist-info/RECORD
