Metadata-Version: 2.4
Name: shllm
Version: 0.0.8
Summary: Natural language shell commands.
Author-email: Ryan Hendry <ryanhendry123@gmail.com>
Requires-Python: >=3.11
Requires-Dist: openai>=1.51.0
Provides-Extra: dev
Requires-Dist: pytest>=8.3.3; extra == 'dev'
